NiuKeyunWeiGongchengshiQiuzhiJingyanFenxiang20212022Fix1/README.md
NiuKeyunWeiGongchengshiQiuzhiJingyanFenxiang20212022Fix1/__init__.py
NiuKeyunWeiGongchengshiQiuzhiJingyanFenxiang20212022Fix1/__main__.py
NiuKeyunWeiGongchengshiQiuzhiJingyanFenxiang20212022Fix1/file.epub
NiuKeyunWeiGongchengshiQiuzhiJingyanFenxiang20212022Fix1/index.html
NiuKeyunWeiGongchengshiQiuzhiJingyanFenxiang20212022Fix1/css/__init__.py
NiuKeyunWeiGongchengshiQiuzhiJingyanFenxiang20212022Fix1/css/annotations.css
NiuKeyunWeiGongchengshiQiuzhiJingyanFenxiang20212022Fix1/css/main.css
NiuKeyunWeiGongchengshiQiuzhiJingyanFenxiang20212022Fix1/css/normalize.css
NiuKeyunWeiGongchengshiQiuzhiJingyanFenxiang20212022Fix1/css/popup.css
NiuKeyunWeiGongchengshiQiuzhiJingyanFenxiang20212022Fix1/font/__init__.py
NiuKeyunWeiGongchengshiQiuzhiJingyanFenxiang20212022Fix1/font/fontello.eot
NiuKeyunWeiGongchengshiQiuzhiJingyanFenxiang20212022Fix1/font/fontello.svg
NiuKeyunWeiGongchengshiQiuzhiJingyanFenxiang20212022Fix1/font/fontello.ttf
NiuKeyunWeiGongchengshiQiuzhiJingyanFenxiang20212022Fix1/font/fontello.woff
NiuKeyunWeiGongchengshiQiuzhiJingyanFenxiang20212022Fix1/img/__init__.py
NiuKeyunWeiGongchengshiQiuzhiJingyanFenxiang20212022Fix1/img/annotator-glyph-sprite.png
NiuKeyunWeiGongchengshiQiuzhiJingyanFenxiang20212022Fix1/img/annotator-icon-sprite.png
NiuKeyunWeiGongchengshiQiuzhiJingyanFenxiang20212022Fix1/img/apple-touch-icon.png
NiuKeyunWeiGongchengshiQiuzhiJingyanFenxiang20212022Fix1/img/cancelfullscreen.png
NiuKeyunWeiGongchengshiQiuzhiJingyanFenxiang20212022Fix1/img/close.png
NiuKeyunWeiGongchengshiQiuzhiJingyanFenxiang20212022Fix1/img/fullscreen.png
NiuKeyunWeiGongchengshiQiuzhiJingyanFenxiang20212022Fix1/img/loader.gif
NiuKeyunWeiGongchengshiQiuzhiJingyanFenxiang20212022Fix1/img/menu-icon.png
NiuKeyunWeiGongchengshiQiuzhiJingyanFenxiang20212022Fix1/img/save.png
NiuKeyunWeiGongchengshiQiuzhiJingyanFenxiang20212022Fix1/img/saved.png
niu_keyun_wei_gongchengshi_qiuzhi_jingyan_fenxiang_2021_2022_fix1-2025.3.25.1.dist-info/METADATA
niu_keyun_wei_gongchengshi_qiuzhi_jingyan_fenxiang_2021_2022_fix1-2025.3.25.1.dist-info/WHEEL
niu_keyun_wei_gongchengshi_qiuzhi_jingyan_fenxiang_2021_2022_fix1-2025.3.25.1.dist-info/entry_points.txt
niu_keyun_wei_gongchengshi_qiuzhi_jingyan_fenxiang_2021_2022_fix1-2025.3.25.1.dist-info/top_level.txt
niu_keyun_wei_gongchengshi_qiuzhi_jingyan_fenxiang_2021_2022_fix1-2025.3.25.1.dist-info/RECORD
